dta.py
dta-1.3.1.dist-info/METADATA
dta-1.3.1.dist-info/WHEEL
dta-1.3.1.dist-info/top_level.txt
dta-1.3.1.dist-info/RECORD
