Metadata-Version: 2.1
Name: dta
Version: 1.3.1
Summary: dta Convert Dict To Attributes!
Home-page: https://github.com/dumb-stuff/dta
Author: Rukchad Wongprayoon
Author-email: contact@biomooping.tk
License: UNKNOWN
Platform: UNKNOWN
Classifier: Programming Language :: Python :: 3
Classifier: License :: OSI Approved :: MIT License
Classifier: Operating System :: OS Independent
Requires-Python: >=2
